optimaldesign/__init__.py
optimaldesign/adaptive_grid_optimal_design.py
optimaldesign/design_measure.py
optimaldesign/interior_point_method.py
optimaldesign/linear_model.py
optimaldesign/optimal_design.py
optimaldesign/tests/__init__.py
optimaldesign/tests/test_linear_model.py
optimaldesign/tests/test_optimal_design.py
optimaldesign-0.1.3.dist-info/LICENSE
optimaldesign-0.1.3.dist-info/METADATA
optimaldesign-0.1.3.dist-info/WHEEL
optimaldesign-0.1.3.dist-info/top_level.txt
optimaldesign-0.1.3.dist-info/RECORD
